[
    {
        "store": "diesel",
        "domain": "co.diesel.com",
        "url": "https://co.diesel.com/",
        "content": [
            {
                "genre": "all",
                "content": [
                    {
                        "category": "watches",
                        "modules": [
                            {
                                "type": "all",
                                "url": "https://co.diesel.com/reloj"
                            }
                        ]
                    }
                ]
            },
            {
                "genre": "women",
                "content": [
                    {
                        "category": "clothes",
                        "modules": [
                            {
                                "type": "t-shirt",
                                "url": "https://co.diesel.com/mujer/denim-y-ropa/ropa/camisetas"
                            },
                            {
                                "type": "jumpsuit",
                                "url": "https://co.diesel.com/mujer/denim-y-ropa/ropa/jumpsuits"
                            },
                            {
                                "type": "shirt",
                                "url": "https://co.diesel.com/mujer/denim-y-ropa/ropa/camisas"
                            },
                            {
                                "type": "sweater",
                                "url": "https://co.diesel.com/mujer/denim-y-ropa/ropa/sweaters"
                            },
                            {
                                "type": "jacket",
                                "url": "https://co.diesel.com/mujer/denim-y-ropa/ropa/chaquetas"
                            },
                            {
                                "type": "pant",
                                "url": "https://co.diesel.com/mujer/denim-y-ropa/ropa/pantalones"
                            },
                            {
                                "type": "underwear",
                                "url": "https://co.diesel.com/mujer/denim-y-ropa/ropa/underwear"
                            },
                            {
                                "type": "skirt",
                                "url": "https://co.diesel.com/mujer/denim-y-ropa/ropa/faldas"
                            },
                            {
                                "type": "dress",
                                "url": "https://co.diesel.com/mujer/denim-y-ropa/ropa/vestidos"
                            },
                            {
                                "type": "short",
                                "url": "https://co.diesel.com/mujer/denim-y-ropa/ropa/shorts"
                            }
                        ]
                    },
                    {
                        "category": "accessories",
                        "modules": [
                            {
                                "type": "bag",
                                "url": "https://co.diesel.com/mujer/zapatos-y-accesorios/bolso"
                            },
                            {
                                "type": "belt",
                                "url": "https://co.diesel.com/mujer/zapatos-y-accesorios/cinturones"
                            }
                        ]
                    },
                    {
                        "category": "shoes",
                        "modules": [
                            {
                                "type": "all",
                                "url": "https://co.diesel.com/mujer/zapatos/zapatos"
                            }
                        ]
                    }
                ]
            },
            {
                "genre": "men",
                "content": [
                    {
                        "category": "shoes",
                        "modules": [
                            {
                                "type": "all",
                                "url": "https://co.diesel.com/hombre/zapatos/zapatos"
                            }
                        ]
                    },
                    {
                        "category": "accessories",
                        "modules": [
                            {
                                "type": "handbag",
                                "url": "https://co.diesel.com/hombre/zapatos-y-accesorios/bolsos"
                            },
                            {
                                "type": "wallet",
                                "url": "https://co.diesel.com/hombre/zapatos-y-accesorios/billeteras"
                            },
                            {
                                "type": "belt",
                                "url": "https://co.diesel.com/hombre/zapatos-y-accesorios/cinturones"
                            },
                            {
                                "type": "fragance",
                                "url": "https://co.diesel.com/hombre/zapatos-y-accesorios/fragancias"
                            },
                            {
                                "type": "hat",
                                "url": "https://co.diesel.com/hombre/gorro"
                            }
                        ]
                    },
                    {
                        "category": "clothes",
                        "modules": [
                            {
                                "type": "t-shirt",
                                "url": "https://co.diesel.com/hombre/denim-y-ropa/ropa/camisetas"
                            },
                            {
                                "type": "polo",
                                "url": "https://co.diesel.com/hombre/denim-y-ropa/ropa/polos"
                            },
                            {
                                "type": "shirt",
                                "url": "https://co.diesel.com/hombre/denim-y-ropa/ropa/camisas"
                            },
                            {
                                "type": "sweater",
                                "url": "https://co.diesel.com/hombre/denim-y-ropa/ropa/sweaters"
                            },
                            {
                                "type": "jacket",
                                "url": "https://co.diesel.com/hombre/denim-y-ropa/ropa/chaquetas"
                            },
                            {
                                "type": "pant",
                                "url": "https://co.diesel.com/hombre/denim-y-ropa/denim"
                            },
                            {
                                "type": "underwear",
                                "url": "https://co.diesel.com/hombre/denim-y-ropa/ropa/underwear"
                            },
                            {
                                "type": "beach",
                                "url": "https://co.diesel.com/hombre/denim-y-ropa/ropa/beach-ware"
                            }
                        ]
                    }
                ]
            }
        ]
    }
]